{
  "name": "Charybdis Nano",
  "vendorProductId": 2834831410,
  "macros": ["", "", "", "", "", "", "", "", "", "", "", "", "", "", "", ""],
  "layers": [
    [
      "KC_Q",
      "KC_W",
      "KC_E",
      "KC_R",
      "KC_T",
      "MT(MOD_LCTL,KC_A)",
      "MT(MOD_LALT,KC_S)",
      "MT(MOD_LGUI,KC_D)",
      "MT(MOD_LSFT,KC_F)",
      "KC_G",
      "LT(4,KC_Z)",
      "KC_X",
      "KC_C",
      "KC_V",
      "KC_B",
      "LT(1,KC_TAB)",
      "KC_NO",
      "LT(3,KC_ESC)",
      "LT(2,KC_SPC)",
      "KC_NO",
      "KC_P",
      "KC_O",
      "KC_I",
      "KC_U",
      "KC_Y",
      "KC_QUOT",
      "MT(MOD_LALT,KC_L)",
      "MT(MOD_LGUI | MOD_RGUI,KC_K)",
      "MT(MOD_LSFT | MOD_RSFT,KC_J)",
      "KC_H",
      "LT(4,KC_SLSH)",
      "KC_DOT",
      "KC_COMM",
      "KC_M",
      "KC_N",
      "LT(6,KC_ENT)",
      "KC_NO",
      "LT(5,KC_BSPC)",
      "KC_NO",
      "KC_NO"
    ],
    [
      "KC_TRNS",
      "KC_TRNS",
      "KC_TRNS",
      "KC_TRNS",
      "KC_TRNS",
      "G(KC_A)",
      "KC_TRNS",
      "KC_TRNS",
      "KC_TRNS",
      "G(KC_F)",
      "G(KC_Z)",
      "G(KC_X)",
      "G(KC_C)",
      "G(KC_V)",
      "KC_TRNS",
      "KC_TRNS",
      "KC_NO",
      "KC_NO",
      "KC_NO",
      "KC_NO",
      "KC_NO",
      "G(KC_RGHT)",
      "KC_UP",
      "G(KC_LEFT)",
      "KC_PGUP",
      "KC_NO",
      "KC_RGHT",
      "KC_DOWN",
      "KC_LEFT",
      "KC_PGDN",
      "KC_NO",
      "KC_NO",
      "KC_NO",
      "KC_NO",
      "KC_NO",
      "KC_NO",
      "KC_NO",
      "KC_DEL",
      "KC_NO",
      "KC_NO"
    ],
    [
      "KC_NO",
      "LAG(KC_LEFT)",
      "G(KC_T)",
      "LAG(KC_RGHT)",
      "G(KC_W)",
      "KC_LCTL",
      "KC_LALT",
      "KC_LGUI",
      "KC_LSFT",
      "KC_NO",
      "KC_NO",
      "KC_MS_BTN4",
      "KC_ENT",
      "KC_MS_BTN5",
      "KC_NO",
      "KC_NO",
      "KC_NO",
      "KC_NO",
      "KC_TRNS",
      "KC_NO",
      "KC_BSLS",
      "KC_9",
      "KC_8",
      "KC_7",
      "KC_GRV",
      "KC_SCLN",
      "KC_6",
      "KC_5",
      "KC_4",
      "KC_MINS",
      "KC_SLSH",
      "KC_3",
      "KC_2",
      "KC_1",
      "KC_EQL",
      "KC_TRNS",
      "KC_NO",
      "KC_0",
      "KC_NO",
      "KC_NO"
    ],
    [
      "KC_NO",
      "KC_MPRV",
      "KC_MPLY",
      "KC_MNXT",
      "KC_NO",
      "KC_LCTL",
      "KC_LALT",
      "KC_LGUI",
      "KC_LSFT",
      "KC_NO",
      "KC_NO",
      "KC_VOLD",
      "KC_MUTE",
      "KC_VOLU",
      "KC_NO",
      "KC_NO",
      "KC_NO",
      "KC_TRNS",
      "KC_NO",
      "KC_NO",
      "KC_F12",
      "KC_F9",
      "KC_F8",
      "KC_F7",
      "KC_NO",
      "KC_F11",
      "KC_F6",
      "KC_F5",
      "KC_F4",
      "KC_NO",
      "KC_F10",
      "KC_F3",
      "KC_F2",
      "KC_F1",
      "KC_NO",
      "KC_NO",
      "KC_NO",
      "KC_NO",
      "KC_NO",
      "KC_NO"
    ],
    [
      "CUSTOM(1)",
      "CUSTOM(0)",
      "KC_ASDN",
      "KC_ASRP",
      "KC_ASUP",
      "KC_LCTL",
      "KC_LALT",
      "KC_LGUI",
      "KC_LSFT",
      "C(S(G(KC_4)))",
      "KC_TRNS",
      "CUSTOM(6)",
      "KC_MS_BTN5",
      "KC_MS_BTN4",
      "LSG(KC_4)",
      "KC_MS_BTN2",
      "KC_NO",
      "CUSTOM(4)",
      "KC_MS_BTN1",
      "KC_NO",
      "CUSTOM(2)",
      "CUSTOM(3)",
      "0x7c71",
      "0x7c70",
      "0x7c72",
      "KC_RCTL",
      "KC_RALT",
      "KC_RGUI",
      "KC_RSFT",
      "KC_F11",
      "KC_TRNS",
      "CUSTOM(6)",
      "KC_MS_BTN5",
      "KC_MS_BTN4",
      "KC_F10",
      "KC_MS_BTN2",
      "KC_NO",
      "KC_MS_BTN1",
      "KC_NO",
      "KC_NO"
    ],
    [
      "KC_NO",
      "RGB_RMOD",
      "RGB_TOG",
      "RGB_MOD",
      "KC_NO",
      "KC_MPRV",
      "KC_VOLD",
      "KC_MUTE",
      "KC_VOLU",
      "KC_MNXT",
      "KC_NO",
      "KC_NO",
      "KC_NO",
      "KC_NO",
      "KC_NO",
      "KC_NO",
      "KC_NO",
      "KC_NO",
      "KC_NO",
      "KC_NO",
      "KC_NO",
      "RGB_MOD",
      "RGB_TOG",
      "RGB_RMOD",
      "KC_NO",
      "KC_MNXT",
      "KC_VOLU",
      "KC_MUTE",
      "KC_VOLD",
      "KC_MPRV",
      "KC_NO",
      "KC_NO",
      "KC_NO",
      "KC_NO",
      "KC_NO",
      "KC_NO",
      "KC_NO",
      "KC_TRNS",
      "KC_NO",
      "KC_NO"
    ],
    [
      "S(KC_LBRC)",
      "S(KC_7)",
      "S(KC_8)",
      "S(KC_9)",
      "S(KC_RBRC)",
      "S(KC_SCLN)",
      "S(KC_4)",
      "S(KC_5)",
      "S(KC_6)",
      "S(KC_EQL)",
      "S(KC_GRV)",
      "S(KC_1)",
      "S(KC_2)",
      "S(KC_3)",
      "S(KC_BSLS)",
      "S(KC_MINS)",
      "KC_NO",
      "S(KC_9)",
      "S(KC_0)",
      "KC_NO",
      "RESET",
      "KC_NO",
      "KC_NO",
      "KC_NO",
      "KC_NO",
      "KC_TRNS",
      "KC_TRNS",
      "KC_TRNS",
      "KC_TRNS",
      "KC_NO",
      "KC_NO",
      "KC_NO",
      "KC_NO",
      "KC_NO",
      "KC_NO",
      "KC_TRNS",
      "KC_NO",
      "KC_NO",
      "KC_NO",
      "KC_NO"
    ]
  ],
  "encoders": []
}